get_adres_data/__init__.py
get_adres_data/functions.py
get_adres_data-0.1.3.7.dist-info/METADATA
get_adres_data-0.1.3.7.dist-info/WHEEL
get_adres_data-0.1.3.7.dist-info/top_level.txt
get_adres_data-0.1.3.7.dist-info/RECORD
