Metadata-Version: 2.1
Name: get_adres_data
Version: 0.1.3.7
Summary: Get ADRES Data in CSV format
Home-page: https://www.adres-risa.org
Author: Joseph Hui
Author-email: joseph-ch.hui@polyu.edu.hk
License: MIT
